{
	"name": "PRE_SDE",
	"properties": {
		"activities": [
			{
				"name": "Execute PRE_SDE BACKUP",
				"type": "ExecutePipeline",
				"dependsOn": [],
				"userProperties": [],
				"typeProperties": {
					"pipeline": {
						"referenceName": "PRE_SDE BACKUP",
						"type": "PipelineReference"
					},
					"waitOnCompletion": true
				}
			},
			{
				"name": "Execute Convert Excel Files",
				"type": "ExecutePipeline",
				"dependsOn": [
					{
						"activity": "Execute PRE_SDE BACKUP",
						"dependencyConditions": [
							"Completed"
						]
					}
				],
				"userProperties": [],
				"typeProperties": {
					"pipeline": {
						"referenceName": "PRE_SDE EXCEL",
						"type": "PipelineReference"
					},
					"waitOnCompletion": true
				}
			}
		],
		"annotations": [],
		"lastPublishTime": "2023-09-21T14:44:36Z"
	},
	"type": "Microsoft.DataFactory/factories/pipelines"
}